venomics_client/__init__.py
venomics_client/client.py
venomics_client/date_ranges.py
venomics_client-0.1.1.dist-info/LICENSE
venomics_client-0.1.1.dist-info/METADATA
venomics_client-0.1.1.dist-info/WHEEL
venomics_client-0.1.1.dist-info/top_level.txt
venomics_client-0.1.1.dist-info/RECORD
