Metadata-Version: 2.1
Name: venomics-client
Version: 0.1.1
Summary: Venomics API Client
Home-page: https://www.venomics.xyz/
Author: maksymds
Author-email: redoubt@devnull.ae
License: MIT
Project-URL: Github, https://github.com/Venomics/venomics-api-client
Project-URL: Documentation, https://www.vebnomics.xyz/
Keywords: Venomics,redoubt,API
Platform: UNKNOWN
Classifier: Development Status :: 4 - Beta
Classifier: Intended Audience :: Developers
Classifier: License :: OSI Approved :: Apache Software License
Classifier: Operating System :: OS Independent
Classifier: Programming Language :: Python :: 3
Classifier: Programming Language :: Python :: 3.6
Classifier: Programming Language :: Python :: 3.8
Classifier: Programming Language :: Python :: 3.9
Classifier: Programming Language :: Python :: 3.10
Classifier: Programming Language :: Python :: 3.11
Classifier: Topic :: Software Development :: Libraries :: Python Modules
Requires-Python: >=3.6
License-File: LICENSE
Requires-Dist: certifi (==2019.9.11)
Requires-Dist: chardet (==3.0.4)
Requires-Dist: idna (==2.8)
Requires-Dist: requests (==2.22.0)
Requires-Dist: urllib3 (==1.25.6)
Requires-Dist: click (==8.0.3)
